Metadata-Version: 1.0
Name: mad-distributions
Version: 1.1
Summary: Probability distributions
Home-page: UNKNOWN
Author: UNKNOWN
Author-email: UNKNOWN
License: UNKNOWN
Platform: UNKNOWN
